{
	"info": {
		"_postman_id": "634adc6d-f661-4f16-8479-7d8dfe9036ab",
		"name": "Amazon",
		"schema": "https://schema.getpostman.com/json/collection/v2.1.0/collection.json"
	},
	"item": [
		{
			"name": "Post Products",
			"request": {
				"method": "POST",
				"header": [],
				"body": {
					"mode": "raw",
					"raw": "[{\r\n    \"productName\": \"OPPO A31(Black, 6GB RAM, 128 GB Storage)\",\r\n    \"productRating\": 4,\r\n    \"productDescription\": \"OPPO A31\",\r\n    \"productPrice\":11490,\r\n    \"productImage\":\"4.png\"\r\n}\r\n]",
					"options": {
						"raw": {
							"language": "json"
						}
					}
				},
				"url": {
					"raw": "http://localhost:4000/products/post-products",
					"protocol": "http",
					"host": [
						"localhost"
					],
					"port": "4000",
					"path": [
						"products",
						"post-products"
					]
				}
			},
			"response": []
		},
		{
			"name": "Get Products",
			"request": {
				"method": "GET",
				"header": [],
				"url": {
					"raw": "http://localhost:4000/products/get-products",
					"protocol": "http",
					"host": [
						"localhost"
					],
					"port": "4000",
					"path": [
						"products",
						"get-products"
					]
				}
			},
			"response": []
		},
		{
			"name": "Sign Up",
			"request": {
				"method": "POST",
				"header": [],
				"body": {
					"mode": "raw",
					"raw": "{\r\n    \"userName\":\"Nikhil\",\r\n    \"userPassword\":\"1234\",\r\n    \"userEmail\":\"admin\",\r\n    \"userPhoneNumber\":1234567890\r\n\r\n}",
					"options": {
						"raw": {
							"language": "json"
						}
					}
				},
				"url": {
					"raw": "http://localhost:4000/sign-up",
					"protocol": "http",
					"host": [
						"localhost"
					],
					"port": "4000",
					"path": [
						"sign-up"
					]
				}
			},
			"response": []
		},
		{
			"name": "Login",
			"request": {
				"method": "POST",
				"header": [],
				"body": {
					"mode": "raw",
					"raw": "{\r\n    \"userEmail\":\"admin\",\r\n    \"userPassword\":\"1234\"\r\n}",
					"options": {
						"raw": {
							"language": "json"
						}
					}
				},
				"url": {
					"raw": "http://localhost:4000/login",
					"protocol": "http",
					"host": [
						"localhost"
					],
					"port": "4000",
					"path": [
						"login"
					]
				}
			},
			"response": []
		}
	]
}